Workbook

Sheet Administracion
B3: en esta seccion que dice administracion solo has una tabla que muestre los datos de las otra tablas
B6: Bancos | C6: 10000
B7: Ingresos | C7: ='Consecutivo 2026'!H256 -> 0 | D7: Facturas por recibir pago.
C8: =C6+C7 -> 10000
B9: Gastos proveedores | C9: ='Pagos de la quincena'!P126 -> 324
C10: =C8-C9 -> 9676
B11: Gastos Ind. | C11: ='Pagos de la quincena'!P127 -> 670
C12: =C10-C11 -> 9006
B13: Nominas | C13: ='Pagos de la quincena'!P128 -> 0
C14: =C12-C13 -> 9006
B15: Impuestos | C15: ='Pagos de la quincena'!P129 -> 0
B16: TOTAL | C16: =C14-C15 -> 9006

Sheet Pagos de la quincena
B2: Folio | D2: Proveedor | E2: Fecha | F2: Servicio | G2: Sub total | H2: IVA | I2: Retencion 4% | J2: Retencion ISR | K2: Total | L2: P | M2: Folio | O2: OP
A3: 1 | D3: Jennifer | F3: Logistica | G3: 150 | H3: =G3*16% -> 24 | I3: 8 | J3: 8 | K3: =G3+H3-I3-J3 -> 158 | L3: P | M3: FE- | Q3: Tipos de folios que el sistema mostrara al usuario cuando el escriba las letras en la seccion Folio el sistema le mostrala o le ayudara a completar el folio
A4: =A3+1 -> 2 | D4: Jennifer | F4: Logistica | H4: =G4*16% -> 0 | K4: =G4+H4-I4-J4 -> 0 | L4: P | M4: FE- | Q4: FE- FLETE
A5: =A4+1 -> 3 | D5: Jennifer | F5: Logistica | G5: 150 | H5: =G5*16% -> 24 | I5: 8 | K5: =G5+H5-I5-J5 -> 166 | L5: P | M5: FE- | Q5: MA- MANIOBRA
A6: =A5+1 -> 4 | D6: Jennifer | F6: Logistica | H6: =G6*16% -> 0 | K6: =G6+H6-I6-J6 -> 0 | L6: P | M6: FE- | Q6: LA- LAVADO
A7: =A6+1 -> 5 | D7: Jennifer | F7: Logistica | H7: =G7*16% -> 0 | K7: =G7+H7-I7-J7 -> 0 | L7: P | M7: FE- | Q7: ES- ESTADIA
A8: =A7+1 -> 6 | D8: Jennifer | F8: Logistica | H8: =G8*16% -> 0 | K8: =G8+H8-I8-J8 -> 0 | L8: P | M8: FE- | Q8: DE-DEMORA
A9: =A7+1 -> 6 | D9: Jennifer | F9: Logistica | H9: =G9*16% -> 0 | K9: =G9+H9-I9-J9 -> 0 | L9: P | M9: FE-
A10: =A8+1 -> 7 | D10: Jennifer | F10: Logistica | H10: =G10*16% -> 0 | K10: =G10+H10-I10-J10 -> 0 | L10: P | M10: FE-
A11: 8 | D11: Jennifer | F11: Logistica | H11: =G11*16% -> 0 | K11: =G11+H11-I11-J11 -> 0 | L11: P | M11: FE-
A12: 9 | D12: Jennifer | F12: Logistica | H12: =G12*16% -> 0 | K12: =G12+H12-I12-J12 -> 0 | L12: P | M12: FE-
A13: 10 | D13: Jennifer | F13: Logistica | H13: =G13*16% -> 0 | K13: =G13+H13-I13-J13 -> 0 | L13: P | M13: FE-
A14: 11 | D14: Jennifer | F14: Logistica | H14: =G14*16% -> 0 | K14: =G14+H14-I14-J14 -> 0 | L14: P | M14: FE-
A15: 12 | D15: Jennifer | F15: Logistica | H15: =G15*16% -> 0 | K15: =G15+H15-I15-J15 -> 0 | L15: P | M15: FE-
A16: 13 | D16: Jennifer | F16: Logistica | H16: =G16*16% -> 0 | K16: =G16+H16-I16-J16 -> 0 | L16: P | M16: FE-
A17: 14 | D17: Jennifer | F17: Logistica | H17: =G17*16% -> 0 | K17: =G17+H17-I17-J17 -> 0 | L17: P | M17: FE-
A18: 15 | D18: Jennifer | F18: Logistica | H18: =G18*16% -> 0 | K18: =G18+H18-I18-J18 -> 0 | L18: P | M18: FE-
A19: 16 | D19: Jennifer | F19: Logistica | H19: =G19*16% -> 0 | K19: =G19+H19-I19-J19 -> 0 | L19: P | M19: FE-
G20: =SUMIF(L3:L19,"P",G3:G19) -> 300 | H20: =SUMIF(L3:L19,"P",H3:H19) -> 48 | I20: =SUMIF(L3:L19,"P",I3:I19) -> 16 | J20: =SUMIF(L3:L19,"P",J3:J19) -> 8 | K20: =SUMIF(L3:L19,"P",K3:K19) -> 324 | M20: todo lo mostrado en azul el sistema no deja que el usuario lo modifique ya que el sistema muestra el resultado
J21: .
B22: Folio | D22: Proveedor | E22: Fecha | F22: Servicio | G22: Sub total | H22: IVA | I22: Retencion 4% | J22: Retencion ISR | K22: Total | L22: P | M22: Folio | O22: OP
A23: =A22+1 -> 1 | B23: FF- | D23: Rama | H23: =G23*16% -> 0 | I23: =G23*4% -> 0 | J23: 0 | K23: =G23+H23-I23-J23 -> 0 | L23: P | M23: FE-
A24: =A23+1 -> 2 | B24: FF- | D24: Rama | H24: =G24*16% -> 0 | I24: =G24*4% -> 0 | J24: 0 | K24: =G24+H24-I24-J24 -> 0 | L24: P | M24: FE-
A25: =A24+1 -> 3 | B25: FF- | D25: Rama | H25: =G25*16% -> 0 | I25: =G25*4% -> 0 | J25: 0 | K25: =G25+H25-I25-J25 -> 0 | L25: P | M25: FE-
A26: =A25+1 -> 4 | B26: FF- | D26: Rama | H26: =G26*16% -> 0 | I26: 0 | J26: 0 | K26: =G26+H26-I26-J26 -> 0 | L26: P | M26: FE-
A27: =A26+1 -> 5 | B27: FF- | D27: Rama | H27: =G27*16% -> 0 | I27: 0 | J27: 0 | K27: =G27+H27-I27-J27 -> 0 | L27: P | M27: FE-
A28: =A27+1 -> 6 | B28: FF- | D28: Rama | H28: =G28*16% -> 0 | I28: =G28*4% -> 0 | J28: 0 | K28: =G28+H28-I28-J28 -> 0 | L28: P | M28: FE-
A29: =A28+1 -> 7 | B29: FF- | D29: Rama | H29: =G29*16% -> 0 | I29: =G29*4% -> 0 | J29: 0 | K29: =G29+H29-I29-J29 -> 0 | L29: P | M29: FE-
A30: =A29+1 -> 8 | B30: FF- | D30: Rama | H30: =G30*16% -> 0 | I30: 0 | J30: 0 | K30: =G30+H30-I30-J30 -> 0 | L30: P | M30: FE-
A31: =A30+1 -> 9 | B31: FF- | D31: Rama | H31: =G31*16% -> 0 | I31: 0 | J31: 0 | K31: =G31+H31-I31-J31 -> 0 | L31: P | M31: FE-
A32: =A31+1 -> 10 | B32: FF- | D32: Rama | H32: =G32*16% -> 0 | J32: 0 | K32: =G32+H32-I32-J32 -> 0 | L32: P | M32: FE-
A33: =A32+1 -> 11 | B33: FF- | D33: Rama | H33: =G33*16% -> 0 | J33: 0 | K33: =G33+H33-I33-J33 -> 0 | L33: P | M33: FE-
A34: =A33+1 -> 12 | B34: FF- | D34: Rama | H34: =G34*16% -> 0 | J34: 0 | K34: =G34+H34-I34-J34 -> 0 | L34: P | M34: FE-
A35: =A34+1 -> 13 | B35: FF- | D35: Rama | H35: =G35*16% -> 0 | J35: 0 | K35: =G35+H35-I35-J35 -> 0 | L35: P | M35: FE-
A36: =A35+1 -> 14 | B36: FF- | D36: Rama | H36: =G36*16% -> 0 | J36: 0 | K36: =G36+H36-I36-J36 -> 0 | L36: P | M36: FE-
A37: =A36+1 -> 15 | B37: FF- | D37: Rama | H37: =G37*16% -> 0 | J37: 0 | K37: =G37+H37-I37-J37 -> 0 | L37: P | M37: FE-
A38: =A37+1 -> 16 | B38: FF- | D38: Rama | H38: =G38*16% -> 0 | J38: 0 | K38: =G38+H38-I38-J38 -> 0 | L38: P | M38: FE-
A39: =A38+1 -> 17 | B39: FF- | D39: Rama | H39: =G39*16% -> 0 | J39: 0 | K39: =G39+H39-I39-J39 -> 0 | L39: P | M39: FE-
A40: =A39+1 -> 18 | B40: FF- | D40: Rama | H40: =G40*16% -> 0 | J40: 0 | K40: =G40+H40-I40-J40 -> 0 | L40: P | M40: FE-
A41: =A40+1 -> 19 | B41: FF- | D41: Rama | H41: =G41*16% -> 0 | J41: 0 | K41: =G41+H41-I41-J41 -> 0 | L41: P | M41: FE-
G42: =SUMIF(L23:L41,"P",G23:G41) -> 0 | H42: =SUMIF(L23:L41,"P",H23:H41) -> 0 | I42: =SUMIF(L23:L41,"P",I23:I41) -> 0 | J42: =SUMIF(L23:L41,"P",J23:J41) -> 0 | K42: =SUMIF(L23:L41,"P",K23:K41) -> 0
B44: Folio | D44: Proveedor | E44: Fecha | F44: Servicio | G44: Sub total | H44: IVA | I44: Retencion 4% | J44: Retencion ISR | K44: Total | L44: P | M44: Folio | O44: OP
A45: =A44+1 -> 1 | D45: Freda | H45: =G45*16% -> 0 | I45: 0 | J45: 0 | K45: =G45+H45-I45-J45 -> 0 | L45: P | M45: FE-
A46: =A45+1 -> 2 | H46: =G46*16% -> 0 | I46: 0 | J46: 0 | K46: =G46+H46-I46-J46 -> 0 | L46: P | M46: FE-
A47: =A46+1 -> 3 | H47: =G47*16% -> 0 | I47: 0 | J47: 0 | K47: =G47+H47-I47-J47 -> 0 | L47: P | M47: FE-
A48: =A47+1 -> 4 | B48: 1- | H48: =G48*16% -> 0 | I48: 0 | J48: 0 | K48: =G48+H48-I48-J48 -> 0 | L48: P | M48: FE-
A49: =A48+1 -> 5 | B49: 1- | H49: =G49*16% -> 0 | I49: 0 | J49: 0 | K49: =G49+H49-I49-J49 -> 0 | L49: P | M49: FE-
A50: =A49+1 -> 6 | B50: 1- | H50: =G50*16% -> 0 | I50: 0 | J50: 0 | K50: =G50+H50-I50-J50 -> 0 | L50: P | M50: FE-
A51: =A50+1 -> 7 | B51: 1- | H51: =G51*16% -> 0 | I51: 0 | J51: 0 | K51: =G51+H51-I51-J51 -> 0 | L51: P | M51: FE-
A52: =A51+1 -> 8 | B52: 1- | H52: =G52*16% -> 0 | I52: 0 | J52: 0 | K52: =G52+H52-I52-J52 -> 0 | L52: P | M52: FE-
A53: =A52+1 -> 9 | B53: 1- | H53: =G53*16% -> 0 | I53: 0 | J53: 0 | K53: =G53+H53-I53-J53 -> 0 | L53: P | M53: FE-
A54: =A53+1 -> 10 | B54: 1- | H54: =G54*16% -> 0 | I54: 0 | J54: 0 | K54: =G54+H54-I54-J54 -> 0 | L54: P | M54: FE-
A55: =A54+1 -> 11 | B55: 1- | H55: =G55*16% -> 0 | I55: 0 | J55: 0 | K55: =G55+H55-I55-J55 -> 0 | L55: P | M55: FE-
A56: =A55+1 -> 12 | B56: 1- | H56: =G56*16% -> 0 | I56: 0 | J56: 0 | K56: =G56+H56-I56-J56 -> 0 | L56: P | M56: FE-
A57: =A56+1 -> 13 | B57: 1- | H57: =G57*16% -> 0 | I57: 0 | J57: 0 | K57: =G57+H57-I57-J57 -> 0 | L57: P | M57: FE-
A58: =A57+1 -> 14 | B58: 1- | H58: =G58*16% -> 0 | I58: 0 | J58: 0 | K58: =G58+H58-I58-J58 -> 0 | L58: P | M58: FE-
A59: =A58+1 -> 15 | B59: 1- | H59: =G59*16% -> 0 | I59: 0 | J59: 0 | K59: =G59+H59-I59-J59 -> 0 | L59: P | M59: FE-
A60: =A59+1 -> 16 | H60: =G60*16% -> 0 | J60: 0 | K60: =G60+H60-I60-J60 -> 0 | L60: P | M60: FE-
A61: =A60+1 -> 17 | H61: =G61*16% -> 0 | J61: 0 | K61: =G61+H61-I61-J61 -> 0 | L61: P | M61: FE-
A62: =A61+1 -> 18 | H62: =G62*16% -> 0 | J62: 0 | K62: =G62+H62-I62-J62 -> 0 | L62: P | M62: FE-
A63: =A62+1 -> 19 | H63: =G63*16% -> 0 | J63: 0 | K63: =G63+H63-I63-J63 -> 0 | L63: P | M63: FE-
G64: =SUMIF(L45:L63,"P",G45:G63) -> 0 | H64: =SUMIF(L45:L63,"P",H45:H63) -> 0 | I64: =SUMIF(L45:L63,"P",I45:I63) -> 0 | J64: =SUMIF(L45:L63,"P",J45:J63) -> 0 | K64: =SUMIF(L45:L63,"P",K45:K63) -> 0
B66: Folio | D66: Proveedor | E66: Fecha | F66: Servicio | G66: Sub total | H66: IVA | I66: Retencion 4% | J66: Retencion ISR | K66: Total | L66: P | M66: Folio | O66: OP
A67: =A66+1 -> 1 | B67: 1- | D67: Victor | H67: =G67*16% -> 0 | I67: 0 | J67: 0 | K67: =G67+H67-I67-J67 -> 0 | L67: P | M67: FE-
A68: =A67+1 -> 2 | H68: =G68*16% -> 0 | J68: 0 | K68: =G68+H68-I68-J68 -> 0 | L68: P | M68: FE-
A69: =A68+1 -> 3 | H69: =G69*16% -> 0 | J69: 0 | K69: =G69+H69-I69-J69 -> 0 | L69: P | M69: FE-
A70: =A69+1 -> 4 | H70: =G70*16% -> 0 | J70: 0 | K70: =G70+H70-I70-J70 -> 0 | L70: P | M70: FE-
A71: =A70+1 -> 5 | H71: =G71*16% -> 0 | J71: 0 | K71: =G71+H71-I71-J71 -> 0 | L71: P | M71: FE-
A72: =A71+1 -> 6 | H72: =G72*16% -> 0 | J72: 0 | K72: =G72+H72-I72-J72 -> 0 | L72: P | M72: FE-
A73: =A72+1 -> 7 | H73: =G73*16% -> 0 | J73: 0 | K73: =G73+H73-I73-J73 -> 0 | L73: P | M73: FE-
A74: =A73+1 -> 8 | H74: =G74*16% -> 0 | J74: 0 | K74: =G74+H74-I74-J74 -> 0 | L74: P | M74: FE-
A75: =A74+1 -> 9 | H75: =G75*16% -> 0 | J75: 0 | K75: =G75+H75-I75-J75 -> 0 | L75: P | M75: FE-
A76: =A75+1 -> 10 | H76: =G76*16% -> 0 | J76: 0 | K76: =G76+H76-I76-J76 -> 0 | L76: P | M76: FE-
G77: =SUMIF(L67:L76,"P",G67:G76) -> 0 | H77: =SUMIF(L67:L76,"P",H67:H76) -> 0 | I77: =SUMIF(L67:L76,"P",I67:I76) -> 0 | J77: =SUMIF(L67:L76,"P",J67:J76) -> 0 | K77: =SUMIF(L67:L76,"P",K67:K76) -> 0
B79: Folio | D79: Proveedor | E79: Fecha | F79: Servicio | G79: Sub total | H79: IVA | I79: Retencion 4% | J79: Retencion ISR | K79: Total | L79: P | M79: Folio | O79: OP | P79: GENERAR PROVEDORES
A80: =A79+1 -> 1 | H80: =G80*16% -> 0 | I80: 0 | J80: 0 | K80: =G80+H80-I80-J80 -> 0 | L80: P | M80: FE-
A81: =A80+1 -> 2 | H81: =G81*16% -> 0 | J81: 0 | K81: =G81+H81-I81-J81 -> 0 | L81: P | M81: FE-
A82: =A81+1 -> 3 | H82: =G82*16% -> 0 | J82: 0 | K82: =G82+H82-I82-J82 -> 0 | L82: P | M82: FE-
A83: =A82+1 -> 4 | H83: =G83*16% -> 0 | J83: 0 | K83: =G83+H83-I83-J83 -> 0 | L83: P | M83: FE-
A84: =A83+1 -> 5 | H84: =G84*16% -> 0 | J84: 0 | K84: =G84+H84-I84-J84 -> 0 | L84: P | M84: FE-
A85: =A84+1 -> 6 | H85: =G85*16% -> 0 | J85: 0 | K85: =G85+H85-I85-J85 -> 0 | L85: P | M85: FE-
A86: =A85+1 -> 7 | H86: =G86*16% -> 0 | J86: 0 | K86: =G86+H86-I86-J86 -> 0 | L86: P | M86: FE-
A87: =A86+1 -> 8 | H87: =G87*16% -> 0 | J87: 0 | K87: =G87+H87-I87-J87 -> 0 | L87: P | M87: FE-
A88: =A87+1 -> 9 | H88: =G88*16% -> 0 | J88: 0 | K88: =G88+H88-I88-J88 -> 0 | L88: P | M88: FE-
A89: =A88+1 -> 10 | H89: =G89*16% -> 0 | J89: 0 | K89: =G89+H89-I89-J89 -> 0 | L89: P | M89: FE-
A90: =A89+1 -> 11 | H90: =G90*16% -> 0 | J90: 0 | K90: =G90+H90-I90-J90 -> 0 | L90: P | M90: FE-
G91: =SUMIF(L80:L90,"P",G80:G90) -> 0 | H91: =SUMIF(L80:L90,"P",H80:H90) -> 0 | I91: =SUMIF(L80:L90,"P",I80:I90) -> 0 | J91: =SUMIF(L80:L90,"P",J80:J90) -> 0 | K91: =SUMIF(L80:L90,"P",K80:K90) -> 0
B92: NOMINAS | Q92: SE VA A MODIFICAR , SOLO MOSTRAR UNA TABLA PARA REVISAR EL COSTO
B93: Folio | D93: Proveedor | E93: Fecha | F93: Servicio | G93: Sub total | H93: IVA | I93: Retencion 4% | J93: Retencion ISR | K93: Total | L93: P | O93: Sub total | P93: Isra
A94: 1 | D94: Fox | E94: 46142 | F94: Nomina | G94: =P94 -> 1060 | H94: 0 | I94: 50 | J94: 0 | K94: 10600 | L94: P | M94: P- POR PAGAR | N94: Fox | O94: 1000 | P94: =O94*1.06 -> 1060
A95: =A94+1 -> 2 | D95: MP | E95: =E94 -> 46142 | F95: Nomina | G95: 0 | H95: 0 | I95: 0 | J95: 0 | K95: =G95+H95-I95-J95 -> 0 | L95: P | M95: X- NO APLICA O PAGADO | N95: MP | O95: 1000 | P95: =O95*1.06 -> 1060
A96: =A95+1 -> 3 | D96: Rex | E96: =E95 -> 46142 | F96: Nomina | G96: 0 | H96: 0 | I96: 0 | J96: 0 | K96: =G96+H96-I96-J96 -> 0 | L96: P | N96: Rex | O96: 1000 | P96: =O96*1.06 -> 1060
A97: =A96+1 -> 4 | D97: RM | E97: =E96 -> 46142 | F97: Nomina | G97: 0 | H97: 0 | I97: 0 | J97: 0 | K97: =G97+H97-I97-J97 -> 0 | L97: P | N97: RM | O97: 1000 | P97: =O97*1.06 -> 1060
A98: =A97+1 -> 5 | E98: =E97 -> 46142 | G98: =P98 -> 0 | H98: 0 | I98: 0 | J98: 0 | K98: =G98+H98-I98-J98 -> 0 | L98: P | P98: =O98*1.06 -> 0
A99: =A98+1 -> 6 | E99: =E98 -> 46142 | G99: =P99 -> 0 | H99: 0 | I99: 0 | J99: 0 | K99: =G99+H99-I99-J99 -> 0 | L99: P | P99: =O99*1.06 -> 0
A100: =A99+1 -> 7 | E100: =E99 -> 46142 | G100: =P100 -> 0 | H100: 0 | I100: 0 | J100: 0 | K100: =G100+H100-I100-J100 -> 0 | L100: X | O100: 0 | P100: =O100*1.06 -> 0
A101: =A100+1 -> 8 | E101: =E100 -> 46142 | G101: =P101 -> 0 | H101: 0 | I101: 0 | J101: 0 | K101: =G101+H101-I101-J101 -> 0 | L101: X | O101: 0 | P101: =O101*1.06 -> 0
G102: =SUMIF(L93:L100,"P",G93:G100) -> 1060 | H102: =SUMIF(L93:L100,"P",H93:H100) -> 0 | I102: =SUMIF(L93:L100,"P",I93:I100) -> 50 | J102: =SUMIF(L93:L100,"P",J93:J100) -> 0 | K102: =SUMIF(L93:L100,"P",K93:K100) -> 10600
B103: INDIRECTOS | O103: =SUM(O94:O101) -> 4000 | P103: =SUM(P94:P101) -> 4240
B104: Folio | D104: Proveedor | E104: Fecha | F104: Servicio | G104: Sub total | H104: IVA | I104: Retencion 4% | J104: Retencion ISR | K104: Total | L104: P | O104: =O95+O96 -> 2000 | P104: =P103-O103 -> 240
...

Sheet Consecutivo 2026
F1: RDP
A2: ENERO 26 | B2: Factura | C2: Fecha de emision | D2: Cliente | F2: Sub total | G2: IVA | H2: Total | I2: ST | J2: Fecha de pago | K2: Referencia OP | L2: Servicio | M2: Servicio | O2: % | P2: Rodipak | Q2: Hugo | R2: Hugo | S2: %
A3: 1 | B3: FE-196 | C3: 46024 | D3: Victor Hugo | E3: 945 | F3: 24720 | G3: =F3*16% -> 3955.2 | H3: =F3+G3 -> 28675.2 | I3: P | J3: 46037 | K3: RD2601001-F | L3: LOCAL CN | O3: =P3/F3 -> 0.27184466 | P3: 6720 | Q3: 1680 | R3: 26400 | S3: =Q3/R3 -> 0.063636364
A4: =A3+1 -> 2 | B4: FE-197 | C4: 46024 | D4: Victor Hugo | E4: 946 | F4: 68200 | G4: =F4*16% -> 10912 | H4: =F4+G4 -> 79112 | I4: P | J4: 46037 | K4: RD2601002-F | L4: Delivery | O4: =P4/F4 -> 0.061583578 | P4: 4200 | Q4: 1800 | R4: 70000 | S4: =Q4/R4 -> 0.025714286
A5: =A4+1 -> 3 | B5: FE-198 | C5: 46028 | D5: Victor Hugo | E5: 947 | F5: 3150 | G5: =F5*16% -> 504 | H5: =F5+G5 -> 3654 | I5: P | J5: 46037 | K5: RD2601-L | L5: Lavado CN | O5: =P5/F5 -> 0.14285714 | P5: 450 | Q5: 450 | R5: 3600 | S5: =Q5/R5 -> 0.125
A6: =A5+1 -> 4 | B6: FE-199 | C6: 46032 | D6: Victor Hugo | E6: 951 | F6: 70400 | G6: =F6*16% -> 11264 | H6: =F6+G6 -> 81664 | I6: P | J6: 46037 | K6: RD2601003-F | L6: Delivery | M6: Apodaca | O6: =P6/F6 -> 0.090909091 | P6: 6400 | Q6: 1600 | R6: 72000 | S6: =Q6/R6 -> 0.022222222
A7: =A6+1 -> 5 | B7: FE-200 | C7: 46032 | D7: Victor Hugo | E7: 952 | F7: 53400 | G7: =F7*16% -> 8544 | H7: =F7+G7 -> 61944 | I7: P | J7: 46037 | K7: RD2601004 | L7: Flete | M7: QRO | O7: =P7/F7 -> 0.11985019 | P7: 6400 | Q7: 1600 | R7: 55000 | S7: =Q7/R7 -> 0.029090909
A8: =A7+1 -> 6 | B8: FE-201 | C8: 46032 | D8: Victor Hugo | E8: 954 | F8: 6200 | G8: =F8*16% -> 992 | H8: =F8+G8 -> 7192 | I8: P | J8: 46037 | K8: RD2601003-F | L8: Peso extra | O8: =P8/F8 -> 0.19354839 | P8: 1200 | Q8: 300 | R8: 6500 | S8: =Q8/R8 -> 0.046153846
A9: =A8+1 -> 7 | B9: FE-202 | C9: 46032 | D9: Victor Hugo | E9: 955 | F9: 6200 | G9: =F9*16% -> 992 | H9: =F9+G9 -> 7192 | I9: P | J9: 46037 | K9: RD2601 | L9: Peso extra | O9: =P9/F9 -> 0.19354839 | P9: 1200 | Q9: 300 | R9: 6500 | S9: =Q9/R9 -> 0.046153846 | T9: =SUM(R3:R9) -> 240000 | U9: =T9*1.16 -> 278400
A10: =A9+1 -> 8 | B10: FE-203 | C10: 46032 | D10: Victor Hugo | E10: 958 | F10: 61800 | G10: =F10*16% -> 9888 | H10: =F10+G10 -> 71688 | I10: P | J10: 46052 | K10: RD2601005-F | L10: Flete | M10: Penstone | O10: =P10/F10 -> 0.077669903 | P10: 4800 | Q10: 1200 | R10: 63000 | S10: =Q10/R10 -> 0.019047619
A11: =A10+1 -> 9 | B11: FE-204 | C11: 46032 | D11: Victor Hugo | E11: 959 | F11: 61800 | G11: =F11*16% -> 9888 | H11: =F11+G11 -> 71688 | I11: P | J11: 46052 | K11: RD2601006-F | L11: Flete | M11: Penstone | O11: =P11/F11 -> 0.077669903 | P11: 4800 | Q11: 1200 | R11: 63000 | S11: =Q11/R11 -> 0.019047619
A12: =A11+1 -> 10 | B12: FE-205 | C12: 46032 | D12: Victor Hugo | E12: 961 | F12: 61800 | G12: =F12*16% -> 9888 | H12: =F12+G12 -> 71688 | I12: P | J12: 46052 | K12: RD2601007-F | L12: Flete | M12: Penstone | O12: =P12/F12 -> 0.077669903 | P12: 4800 | Q12: 1200 | R12: 63000 | S12: =Q12/R12 -> 0.019047619
A13: =A12+1 -> 11 | B13: FE-206 | C13: 46032 | D13: Victor Hugo | E13: 962 | F13: 40150 | G13: =F13*16% -> 6424 | H13: =F13+G13 -> 46574 | I13: P | J13: 46052 | K13: RD2601008-F | L13: Flete | M13: Penstone | O13: =P13/F13 -> 0.11955168 | P13: 4800 | Q13: 1200 | R13: 41500 | S13: =Q13/R13 -> 0.028915663
A14: =A13+1 -> 12 | B14: FE-207 | C14: 46032 | D14: Victor Hugo | E14: 963 | F14: 53800 | G14: =F14*16% -> 8608 | H14: =F14+G14 -> 62408 | I14: P | J14: 46052 | K14: RD2601009-F | L14: Flete | M14: SLP | O14: =P14/F14 -> 0.14498141 | P14: 7800 | Q14: 1200 | R14: 55000 | S14: =Q14/R14 -> 0.021818182
A15: =A14+1 -> 13 | B15: FE-208 | C15: 46035 | D15: Victor Hugo | E15: 943 | F15: 525 | G15: =F15*16% -> 84 | H15: =F15+G15 -> 609 | I15: P | J15: 46037 | L15: Lavado CN | O15: =P15/F15 -> 0.14285714 | P15: 75 | Q15: 75 | R15: 600 | S15: =Q15/R15 -> 0.125
A16: =A15+1 -> 14 | B16: FE-209 | C16: 46037 | D16: Victor Hugo | E16: 965 | F16: 2550 | G16: =F16*16% -> 408 | H16: =F16+G16 -> 2958 | I16: P | J16: 46052 | K16: RD2601012-F | L16: LOCAL CN | O16: =P16/F16 -> 0.1372549 | P16: 350 | Q16: 150 | R16: 2700 | S16: =Q16/R16 -> 0.055555556
A17: =A16+1 -> 15 | B17: FE-210 | C17: 46037 | D17: Victor Hugo | E17: 967 | F17: 3150 | G17: =F17*16% -> 504 | H17: =F17+G17 -> 3654 | I17: P | J17: 46052 | K17: RD260-L | L17: Lavado CN | O17: =P17/F17 -> 0.14285714 | P17: 450 | Q17: 450 | R17: 3600 | S17: =Q17/R17 -> 0.125
A18: =A17+1 -> 16 | B18: FE-211 | C18: 46037 | D18: Victor Hugo | E18: 968 | F18: 525 | G18: =F18*16% -> 84 | H18: =F18+G18 -> 609 | I18: P | J18: 46052 | K18: RD260-L | L18: Lavado CN | O18: =P18/F18 -> 0.14285714 | P18: 75 | Q18: 75 | R18: 600 | S18: =Q18/R18 -> 0.125
A19: =A18+1 -> 17 | B19: FE-212 | C19: 46037 | D19: Victor Hugo | E19: 971 | F19: 16480 | G19: =F19*16% -> 2636.8 | H19: =F19+G19 -> 19116.8 | I19: P | J19: 46052 | K19: RD260101011-F | L19: LOCAL CN | O19: =P19/F19 -> 0.27184466 | P19: 4480 | Q19: 1120 | R19: 17600 | S19: =Q19/R19 -> 0.063636364
A20: =A19+1 -> 18 | B20: FE-213 | C20: 46037 | D20: Victor Hugo | E20: 972 | F20: 17750 | G20: =F20*16% -> 2840 | H20: =F20+G20 -> 20590 | I20: P | J20: 46052 | K20: RD2601010-F | L20: Flete | O20: =P20/F20 -> 0.098591549 | P20: 1750 | Q20: 120 | R20: 18500 | S20: =Q20/R20 -> 0.0064864865
A21: =A20+1 -> 19 | B21: FE-214 | C21: 46038 | D21: Express | E21: NA | F21: 1000 | G21: =F21*16% -> 160 | H21: =F21+G21 -> 1160 | I21: P | J21: 46052 | K21: RET | L21: RET | O21: =P21/F21 -> 1 | P21: 1000 | Q21: 0 | R21: 0 | S21: =Q21/R21 -> #DIV/0!
A22: =A21+1 -> 20 | B22: FE-215 | C22: 46038 | D22: Victor Hugo | E22: 976 | F22: 4200 | G22: =F22*16% -> 672 | H22: =F22+G22 -> 4872 | I22: P | J22: 46052 | K22: RD2601013-L | L22: Lavado CN | O22: =P22/F22 -> 0.14285714 | P22: 600 | Q22: 600 | R22: 4800 | S22: =Q22/R22 -> 0.125
A23: =A22+1 -> 21 | B23: FE-216 | C23: Cancelado | D23: Cancelado | F23: 0 | G23: =F23*16% -> 0 | H23: =F23+G23 -> 0 | I23: P | J23: Cancelado | K23: Cancelado | L23: Cancelado | M23: Cancelado | O23: Cancelado | P23: Cancelado | Q23: Cancelado | R23: Cancelado | S23: Cancelado
A24: =A23+1 -> 22 | B24: FE-217 | C24: Cancelado | D24: Cancelado | F24: 0 | G24: =F24*16% -> 0 | H24: =F24+G24 -> 0 | I24: P | J24: Cancelado | K24: Cancelado | L24: Cancelado | M24: Cancelado | O24: Cancelado | P24: Cancelado | Q24: Cancelado | R24: Cancelado | S24: Cancelado
A25: =A24+1 -> 23 | B25: FE-218 | C25: 46042 | D25: Victor Hugo | E25: 978 | F25: 3150 | G25: =F25*16% -> 504 | H25: =F25+G25 -> 3654 | I25: P | J25: 46052 | K25: RD2601014-L | L25: Lavado CN | O25: =P25/F25 -> 0.14285714 | P25: 450 | Q25: 450 | R25: 3600 | S25: =Q25/R25 -> 0.125
A26: =A25+1 -> 24 | B26: FE-219 | C26: 46042 | D26: Victor Hugo | E26: 979 | F26: 1060 | G26: =F26*16% -> 169.6 | H26: =F26+G26 -> 1229.6 | I26: P | J26: 46052 | K26: RD2601015-L | L26: Lavado CN | O26: =P26/F26 -> 0.14150943 | P26: 150 | Q26: 150 | R26: 1200 | S26: =Q26/R26 -> 0.125
A27: =A26+1 -> 25 | B27: FE-220 | C27: 46043 | D27: Victor Hugo | E27: 983 | F27: 40375 | G27: =F27*16% -> 6460 | H27: =F27+G27 -> 46835 | I27: P | J27: 46052 | K27: RD2601015-F | L27: Flete | O27: =P27/F27 -> 0.083591331 | P27: 3375 | Q27: 1125 | R27: 41500 | S27: =Q27/R27 -> 0.027108434
A28: =A27+1 -> 26 | B28: FE-221 | C28: 46043 | D28: Victor Hugo | E28: 984 | F28: 67375 | G28: =F28*16% -> 10780 | H28: =F28+G28 -> 78155 | I28: P | J28: 46052 | K28: RD2601016-F | L28: Flete | O28: =P28/F28 -> 0.050092764 | P28: 3375 | Q28: 1125 | R28: 68500 | S28: =Q28/R28 -> 0.016423358
A29: =A28+1 -> 27 | B29: FE-222 | C29: 46044 | D29: Victor Hugo | E29: 986 | F29: 4130 | G29: =F29*16% -> 660.8 | H29: =F29+G29 -> 4790.8 | I29: P | J29: 46052 | K29: RD2601017-F | L29: LOCAL CN | O29: =P29/F29 -> 0.15254237 | P29: 630 | Q29: 270 | R29: 4400 | S29: =Q29/R29 -> 0.061363636
A30: =A29+1 -> 28 | B30: FE-223 | C30: Cancelado | D30: Cancelado | F30: 0 | G30: =F30*16% -> 0 | H30: =F30+G30 -> 0 | I30: P | J30: Cancelado | K30: Cancelado | L30: Cancelado | M30: Cancelado | O30: Cancelado | P30: Cancelado | Q30: Cancelado | R30: Cancelado | S30: Cancelado
A31: =A30+1 -> 29 | B31: FE-224 | C31: 46045 | D31: Victor Hugo | E31: 989 | F31: 23050 | G31: =F31*16% -> 3688 | H31: =F31+G31 -> 26738 | I31: P | J31: 46052 | K31: RD2601018-F | L31: FTL | M31: Caja seca | O31: =P31/F31 -> 0.045553145 | P31: 1050 | Q31: 450 | R31: 23500 | S31: =Q31/R31 -> 0.019148936
A32: =A31+1 -> 30 | B32: FE-225 | C32: 46045 | D32: Victor Hugo | E32: 990 | F32: 70400 | G32: =F32*16% -> 11264 | H32: =F32+G32 -> 81664 | I32: P | J32: 46052 | K32: RD2601019-F | L32: Flete | O32: =P32/F32 -> 0.090909091 | P32: 6400 | Q32: 1600 | R32: 72000 | S32: =Q32/R32 -> 0.022222222
A33: =A32+1 -> 31 | B33: FE-226 | C33: 46045 | D33: Victor Hugo | E33: 991 | F33: 6050 | G33: =F33*16% -> 968 | H33: =F33+G33 -> 7018 | I33: P | J33: 46052 | K33: ESTADIA | L33: Estadia | O33: =P33/F33 -> 0.17355372 | P33: 1050 | Q33: 450 | R33: 6500 | S33: =Q33/R33 -> 0.069230769
A34: =A33+1 -> 32 | B34: FE-227 | C34: 46046 | D34: Victor Hugo | E34: 992 | F34: 525 | G34: =F34*16% -> 84 | H34: =F34+G34 -> 609 | I34: P | J34: 46052 | K34: RD2601020-L | L34: Lavado CN | O34: =P34/F34 -> 0.14285714 | P34: 75 | Q34: 75 | R34: 600 | S34: =Q34/R34 -> 0.125
A35: =A34+1 -> 33 | B35: FE-228 | C35: 46049 | D35: Victor Hugo | E35: 994 | F35: 1050 | G35: =F35*16% -> 168 | H35: =F35+G35 -> 1218 | I35: P | J35: 46052 | K35: RD2621001-L | L35: Lavado CN | O35: =P35/F35 -> 0.14285714 | P35: 150 | Q35: 150 | R35: 1200 | S35: =Q35/R35 -> 0.125
A36: =A35+1 -> 34 | B36: FE-229 | C36: 46057 | D36: Victor Hugo | E36: 999 | F36: 13850 | G36: =F36*16% -> 2216 | H36: =F36+G36 -> 16066 | I36: P | J36: 46066 | K36: RDP2601021-F | L36: LOCAL CN | M36: 380-Jennifer | O36: =P36/F36 -> 0.20577617 | P36: 2850 | Q36: 850 | R36: 14700 | S36: =Q36/R36 -> 0.057823129
A37: =A36+1 -> 35 | B37: FE-230 | C37: 46057 | D37: Victor Hugo | E37: 1-102 | F37: 525 | G37: =F37*16% -> 84 | H37: =F37+G37 -> 609 | I37: P | J37: 46066 | K37: RDP2601001-L | L37: Lavado CN | M37: FF-311-Rama | O37: =P37/F37 -> 0.14285714 | P37: 75 | Q37: 75 | R37: 600 | S37: =Q37/R37 -> 0.125
A38: =A37+1 -> 36 | B38: FE-231 | C38: 46057 | D38: Victor Hugo | E38: 1-104 | F38: 1800 | G38: =F38*16% -> 288 | H38: =F38+G38 -> 2088 | I38: P | J38: 46066 | K38: RDP-2601002-L | L38: Lavado CN | M38: FF-312-Rama | O38: =P38/F38 -> 0.25 | P38: 450 | Q38: 0 | R38: 1800 | S38: =Q38/R38 -> 0
A39: =A38+1 -> 37 | B39: FE-232 | C39: 46057 | D39: N/A | E39: N/A | F39: 1200 | G39: =F39*16% -> 192 | H39: =F39+G39 -> 1392 | I39: P | J39: 46058 | K39: Express | L39: Express | M39: Express | O39: =P39/F39 -> 1 | P39: 1200 | Q39: 0 | R39: 0 | S39: 0
A40: =A39+1 -> 38 | B40: FE-233 | C40: 46057 | D40: Victor Hugo | E40: 1-107 | F40: 97000 | G40: =F40*16% -> 15520 | H40: =F40+G40 -> 112520 | I40: P | J40: 46066 | K40: RDP2602022-F | L40: Flete | M40: FF-315-Rama | O40: =P40/F40 -> 0.041237113 | P40: 4000 | Q40: 1000 | R40: 98000 | S40: =Q40/R40 -> 0.010204082
A41: =A40+1 -> 39 | B41: FE-234 | C41: 46057 | D41: Victor Hugo | E41: 1-108 | F41: 66000 | G41: =F41*16% -> 10560 | H41: =F41+G41 -> 76560 | I41: P | J41: 46066 | K41: RDP2602023-F | L41: Flete | M41: FF-314-Rama | O41: =P41/F41 -> 0.060606061 | P41: 4000 | Q41: 1000 | R41: 67000 | S41: =Q41/R41 -> 0.014925373
A42: =A41+1 -> 40 | B42: FE-235 | C42: 46057 | D42: Victor Hugo | E42: 1-109 | F42: 4130 | G42: =F42*16% -> 660.8 | H42: =F42+G42 -> 4790.8 | I42: P | J42: 46066 | K42: RDP2602024-F | L42: Flete | M42: FF-317-Rama | O42: =P42/F42 -> 0.031476998 | P42: 130 | Q42: 270 | R42: 4400 | S42: =Q42/R42 -> 0.061363636
A43: =A42+1 -> 41 | B43: FE-236 | C43: 46057 | D43: Victor Hugo | E43: 1-110 | F43: 49800 | G43: =F43*16% -> 7968 | H43: =F43+G43 -> 57768 | I43: P | J43: 46066 | K43: ROD2602025-F | L43: Flete | M43: FF-316-Rama | O43: =P43/F43 -> 0.0562249 | P43: 2800 | Q43: 1200 | R43: 51000 | S43: =Q43/R43 -> 0.023529412
A44: =A43+1 -> 42 | B44: FE-237 | D44: Express | G44: =F44*16% -> 0 | H44: =F44+G44 -> 0 | I44: P | J44: 46066 | O44: =P44/F44 -> #DIV/0! | S44: =Q44/R44 -> #DIV/0!
A45: =A44+1 -> 43 | B45: FE-238 | D45: Victor Hugo | G45: =F45*16% -> 0 | H45: =F45+G45 -> 0 | I45: P | J45: 46066 | O45: =P45/F45 -> #DIV/0! | S45: =Q45/R45 -> #DIV/0!
A46: =A45+1 -> 44 | B46: FE-239 | C46: 46065 | D46: Victor Hugo | E46: 1-117 | F46: 40150 | G46: =F46*16% -> 6424 | H46: =F46+G46 -> 46574 | I46: P | J46: 46080 | K46: RDP2602026F | L46: Flete | M46: FF-328-Rama | O46: =P46/F46 -> 0.078455791 | P46: 3150 | Q46: 1350 | R46: 41500 | S46: =Q46/R46 -> 0.03253012
A47: =A46+1 -> 45 | B47: FE-240 | C47: 46070 | D47: Victor Hugo | E47: 1-120 | F47: 7960 | G47: =F47*16% -> 1273.6 | H47: =F47+G47 -> 9233.6 | I47: P | J47: 46080 | K47: RDP2602027-F | L47: Lavado CN | M47: 389-Omar | O47: =P47/F47 -> 0.24623116 | P47: 1960 | Q47: 840 | R47: 8800 | S47: =Q47/R47 -> 0.095454545
A48: =A47+1 -> 46 | B48: FE-241 | C48: 46070 | D48: Victor Hugo | E48: 1-121 | F48: 8960 | G48: =F48*16% -> 1433.6 | H48: =F48+G48 -> 10393.6 | I48: P | J48: 46080 | K48: RDP2602028-F | L48: LOCAL CN | M48: 389-Omar | O48: =P48/F48 -> 0.21875 | P48: 1960 | Q48: 840 | R48: 9800 | S48: =Q48/R48 -> 0.085714286
A49: =A48+1 -> 47 | B49: FE-242 | C49: 46070 | D49: Victor Hugo | E49: 1-122 | F49: 8960 | G49: =F49*16% -> 1433.6 | H49: =F49+G49 -> 10393.6 | I49: P | J49: 46080 | K49: RDP2602029-F | L49: LOCAL CN | M49: 389-Omar | O49: =P49/F49 -> 0.21875 | P49: 1960 | Q49: 840 | R49: 9800 | S49: =Q49/R49 -> 0.085714286
A50: =A49+1 -> 48 | B50: FE-243 | C50: 46070 | D50: Victor Hugo | E50: 1-124 | F50: 2625 | G50: =F50*16% -> 420 | H50: =F50+G50 -> 3045 | I50: P | J50: 46080 | K50: RDP2602004-L | L50: Lavado CN | M50: FF-331-RAMA | O50: =P50/F50 -> 0.14285714 | P50: 375 | Q50: 375 | R50: 3000 | S50: =Q50/R50 -> 0.125
A51: =A50+1 -> 49 | B51: FE-244 | C51: 46070 | D51: Victor Hugo | E51: 1-125 | F51: 53400 | G51: =F51*16% -> 8544 | H51: =F51+G51 -> 61944 | I51: P | J51: 46080 | K51: RDP2602030-F | L51: Flete | M51: FF-Rama | O51: =P51/F51 -> 0.11985019 | P51: 6400 | Q51: 1600 | R51: 55000 | S51: =Q51/R51 -> 0.029090909
A52: =A51+1 -> 50 | B52: FE-245 | C52: 46074 | D52: Victor Hugo | E52: 1-127 | F52: 70400 | G52: =F52*16% -> 11264 | H52: =F52+G52 -> 81664 | I52: P | J52: 46080 | K52: RDP2602032-F | L52: Flete | M52: FF-Rama | O52: =P52/F52 -> 0.090909091 | P52: 6400 | Q52: 1600 | R52: 72000 | S52: =Q52/R52 -> 0.022222222
A53: =A52+1 -> 51 | B53: FE-246 | C53: 46074 | D53: Victor Hugo | E53: 1-130 | F53: 61800 | G53: =F53*16% -> 9888 | H53: =F53+G53 -> 71688 | I53: P | J53: 46080 | K53: RDP2602033-F | O53: =P53/F53 -> 0.077669903 | P53: 4800 | Q53: 1200 | R53: 73080 | S53: =Q53/R53 -> 0.016420361
A54: =A53+1 -> 52 | B54: FE-247 | C54: 46074 | D54: Victor Hugo | E54: 1-131 | F54: 61800 | G54: =F54*16% -> 9888 | H54: =F54+G54 -> 71688 | I54: P | J54: 46080 | K54: N/A | O54: =P54/F54 -> 0.077669903 | P54: 4800 | Q54: 1200 | R54: 73080 | S54: =Q54/R54 -> 0.016420361
A55: =A54+1 -> 53 | B55: FE-248 | C55: 46079 | D55: Express | G55: =F55*16% -> 0 | H55: =F55+G55 -> 0 | I55: P | J55: 46080 | K55: N/A | O55: =P55/F55 -> #DIV/0! | S55: =Q55/R55 -> #DIV/0!
A56: =A55+1 -> 54 | B56: FE-249 | C56: 46084 | D56: Victor Hugo | E56: 1-133 | F56: 1050 | G56: =F56*16% -> 168 | H56: =F56+G56 -> 1218 | I56: P | J56: 46094 | K56: RDP2603005-L | L56: Lavado CN | O56: =P56/F56 -> 0.14285714 | P56: 150 | Q56: 150 | R56: 1200 | S56: =Q56/R56 -> 0.125
A57: =A56+1 -> 55 | B57: FE-250 | C57: 46084 | D57: Victor Hugo | E57: 1-135 | F57: 1475 | G57: =F57*16% -> 236 | H57: =F57+G57 -> 1711 | I57: P | J57: 46094 | K57: RDP2602006-L | L57: Lavado CN | O57: =P57/F57 -> 0.28813559 | P57: 425 | Q57: 425 | R57: 1900 | S57: =Q57/R57 -> 0.22368421
A58: =A57+1 -> 56 | B58: FE-251 | C58: 46084 | D58: Victor Hugo | E58: 1-139 | F58: 28200 | G58: =F58*16% -> 4512 | H58: =F58+G58 -> 32712 | I58: P | J58: 46094 | O58: =P58/F58 -> 0.18439716 | P58: 5200 | Q58: 1300 | R58: 29500 | S58: =Q58/R58 -> 0.044067797
A59: =A58+1 -> 57 | B59: FE-252 | C59: 46094 | D59: Express | E59: N/A | F59: 825 | G59: =F59*16% -> 132 | H59: =F59+G59 -> 957 | I59: P | O59: =P59/F59 -> 0 | S59: =Q59/R59 -> #DIV/0!
A60: =A59+1 -> 58 | B60: FE-253 | C60: 46095 | D60: Victor Hugo | E60: 1-143 | F60: 4620 | G60: =F60*16% -> 739.2 | H60: =F60+G60 -> 5359.2 | I60: P | J60: 46112 | K60: RDP2603035-F | L60: FLETE | M60: OMAR404 | O60: =P60/F60 -> 0.24242424 | P60: 1120 | Q60: 280 | R60: 5684 | S60: =Q60/R60 -> 0.049261084
A61: =A60+1 -> 59 | B61: FE-254 | C61: 46095 | D61: Victor Hugo | E61: 1-144 | F61: 9240 | G61: =F61*16% -> 1478.4 | H61: =F61+G61 -> 10718.4 | I61: P | J61: 46112 | K61: RDP2603036-F | L61: FLETE | M61: OMAR404 | O61: =P61/F61 -> 0.24242424 | P61: 2240 | Q61: 560 | R61: 11368 | S61: =Q61/R61 -> 0.049261084
A62: =A61+1 -> 60 | B62: FE-255 | C62: 46095 | D62: Victor Hugo | E62: 1-145 | F62: 40150 | G62: =F62*16% -> 6424 | H62: =F62+G62 -> 46574 | I62: P | J62: 46112 | K62: RDP2603037-F | L62: FLETE | M62: RAMA | O62: =P62/F62 -> 0.078455791 | P62: 3150 | Q62: 1350 | R62: 41500 | S62: =Q62/R62 -> 0.03253012
A63: =A62+1 -> 61 | B63: FE-256 | C63: 46095 | D63: Victor Hugo | E63: 1-146 | F63: 60500 | G63: =F63*16% -> 9680 | H63: =F63+G63 -> 70180 | I63: P | J63: 46112 | K63: RDP2603038-F | L63: FLETE | M63: RAMA | O63: =P63/F63 -> 0.05785124 | P63: 3500 | Q63: 1500 | R63: 62000 | S63: =Q63/R63 -> 0.024193548
A64: =A63+1 -> 62 | B64: FE-257 | C64: 46095 | D64: Victor Hugo | E64: 1-148 | F64: 3050 | G64: =F64*16% -> 488 | H64: =F64+G64 -> 3538 | I64: P | J64: 46112 | K64: RDP2603007-L | L64: Lavado CN | M64: RAMA | O64: =P64/F64 -> 0.21311475 | P64: 650 | Q64: 650 | R64: 3700 | S64: =Q64/R64 -> 0.17567568
A65: =A64+1 -> 63 | B65: FE-258 | C65: 46095 | D65: Victor Hugo | E65: 1-149 | F65: 55380 | G65: =F65*16% -> 8860.8 | H65: =F65+G65 -> 64240.8 | I65: P | J65: 46112 | K65: RDP26030339-F | L65: FLETE | M65: OMAR404 | O65: =P65/F65 -> 0.34994583 | P65: 19380 | Q65: 3420 | R65: 58800 | S65: =Q65/R65 -> 0.058163265
A66: =A65+1 -> 64 | B66: FE-259 | C66: 46095 | D66: Victor Hugo | E66: 1-152 | F66: 4200 | G66: =F66*16% -> 672 | H66: =F66+G66 -> 4872 | I66: P | J66: 46112 | K66: RDP2603008-L | L66: Lavado CN | M66: RAMA | O66: =P66/F66 -> 0.14285714 | P66: 600 | Q66: 600 | R66: 4800 | S66: =Q66/R66 -> 0.125
A67: =A66+1 -> 65 | B67: FE-260 | C67: 46099 | D67: Victor Hugo | E67: 1-154 | F67: 9040 | G67: =F67*16% -> 1446.4 | H67: =F67+G67 -> 10486.4 | I67: P | J67: 46112 | K67: RDP2603040-F | L67: LOCAL CN | M67: Omar | O67: =P67/F67 -> 0.33628319 | P67: 3040 | Q67: 760 | R67: 9800 | S67: =Q67/R67 -> 0.07755102
A68: =A67+1 -> 66 | B68: FE-261 | C68: 46099 | D68: Victor Hugo | E68: 1-155 | F68: 1050 | G68: =F68*16% -> 168 | H68: =F68+G68 -> 1218 | I68: P | J68: 46112 | K68: RDP2603009-L | L68: Lavado CN | M68: RAMA | O68: =P68/F68 -> 0.14285714 | P68: 150 | Q68: 150 | R68: 1200 | S68: =Q68/R68 -> 0.125
A69: =A68+1 -> 67 | B69: FE-262 | C69: 46100 | D69: Victor Hugo | E69: 1-157 | F69: 1050 | G69: =F69*16% -> 168 | H69: =F69+G69 -> 1218 | I69: P | J69: 46112 | K69: RDP2603010-L | L69: Lavado CN | M69: RAMA | O69: =P69/F69 -> 0.14285714 | P69: 150 | Q69: 150 | R69: 1200 | S69: =Q69/R69 -> 0.125
A70: =A69+1 -> 68 | B70: FE-263 | C70: 46100 | D70: Victor Hugo | E70: 1-160 | F70: 4710 | G70: =F70*16% -> 753.6 | H70: =F70+G70 -> 5463.6 | I70: P | J70: 46112 | K70: RDP2603041-M | L70: Maniobras | M70: RAMA | O70: =P70/F70 -> 0.044585987 | P70: 210 | Q70: 90 | R70: 4800 | S70: =Q70/R70 -> 0.01875
A71: =A70+1 -> 69 | B71: FE-264 | C71: 46100 | D71: Victor Hugo | E71: 1-161 | F71: 67150 | G71: =F71*16% -> 10744 | H71: =F71+G71 -> 77894 | I71: P | J71: 46112 | K71: RDP2603042-F | L71: Flete | M71: RAMA | O71: =P71/F71 -> 0.046909903 | P71: 3150 | Q71: 1350 | R71: 68500 | S71: =Q71/R71 -> 0.019708029
A72: =A71+1 -> 70 | B72: FE-265 | C72: 46102 | D72: Victor Hugo | E72: 1-163 | F72: 61000 | G72: =F72*16% -> 9760 | H72: =F72+G72 -> 70760 | I72: P | J72: 46127 | L72: Flete | M72: RAMA | O72: =P72/F72 -> 0.06557377 | P72: 4000 | Q72: 1000 | R72: 62000 | S72: =Q72/R72 -> 0.016129032
A73: =A72+1 -> 71 | B73: FE-266 | C73: 46108 | D73: Express | F73: 900 | G73: =F73*16% -> 144 | H73: =F73+G73 -> 1044 | I73: P | J73: 46112 | K73: N/A | L73: Otro | M73: Otro | O73: =P73/F73 -> 1 | P73: 900 | Q73: 0 | R73: 0 | S73: =Q73/R73 -> #DIV/0!
A74: =A73+1 -> 72 | B74: FE-267 | C74: 46111 | D74: Victor Hugo | E74: 1-166 | F74: 525 | G74: =F74*16% -> 84 | H74: =F74+G74 -> 609 | I74: P | J74: 46127 | L74: Lavado CN | M74: RAMA | O74: =P74/F74 -> 0.14285714 | P74: 75 | Q74: 75 | R74: 600 | S74: =Q74/R74 -> 0.125
A75: =A74+1 -> 73 | B75: FE-268 | C75: 46111 | D75: Victor Hugo | E75: 1-167 | F75: 1050 | G75: =F75*16% -> 168 | H75: =F75+G75 -> 1218 | I75: P | J75: 46127 | L75: Lavado CN | M75: RAMA | O75: =P75/F75 -> 0.14285714 | P75: 150 | Q75: 150 | R75: 1200 | S75: =Q75/R75 -> 0.125
A76: =A75+1 -> 74 | B76: FE-269 | C76: 46120 | D76: Victor Hugo | E76: 1-170 | F76: 2550 | G76: =F76*16% -> 408 | H76: =F76+G76 -> 2958 | I76: P | J76: 46127 | L76: LOCAL CN | M76: Jenny | O76: =P76/F76 -> 0.1372549 | P76: 350 | Q76: 150 | R76: 2700 | S76: =Q76/R76 -> 0.055555556
A77: =A76+1 -> 75 | B77: FE-270 | C77: 46120 | D77: Victor Hugo | E77: 1-173 | F77: 98400 | G77: =F77*16% -> 15744 | H77: =F77+G77 -> 114144 | I77: P | J77: 46127 | L77: LOCAL CN | M77: Jenny | O77: =P77/F77 -> 0.3546748 | P77: 34900 | Q77: 4500 | R77: 102900 | S77: =Q77/R77 -> 0.043731778
A78: =A77+1 -> 76 | B78: FE-271 | C78: 46120 | D78: Victor Hugo | E78: 1-177 | F78: 49800 | G78: =F78*16% -> 7968 | H78: =F78+G78 -> 57768 | I78: P | J78: 46127 | L78: Flete | M78: RAMA | O78: =P78/F78 -> 0.15662651 | P78: 7800 | Q78: 1200 | R78: 51000 | S78: =Q78/R78 -> 0.023529412
A79: =A78+1 -> 77 | B79: FE-272 | C79: 46120 | D79: Victor Hugo | E79: 1-179 | F79: 42000 | G79: =F79*16% -> 6720 | H79: =F79+G79 -> 48720 | I79: P | J79: 46127 | L79: Flete | M79: Jenny | O79: =P79/F79 -> 0 | R79: 42000 | S79: =Q79/R79 -> 0
A80: =A79+1 -> 78 | B80: FE-273 | C80: 46120 | D80: Victor Hugo | E80: 1-180 | F80: 61800 | G80: =F80*16% -> 9888 | H80: =F80+G80 -> 71688 | I80: P | J80: 46127 | L80: Flete | M80: RAMA | O80: =P80/F80 -> 0.077669903 | P80: 4800 | Q80: 1200 | R80: 63000 | S80: =Q80/R80 -> 0.019047619
A81: =A80+1 -> 79 | B81: FE-274 | C81: 46120 | D81: Victor Hugo | E81: 1-181 | F81: 53800 | G81: =F81*16% -> 8608 | H81: =F81+G81 -> 62408 | I81: P | J81: 46127 | L81: Flete | M81: RAMA | O81: =P81/F81 -> 0.14498141 | P81: 7800 | Q81: 1200 | R81: 55000 | S81: =Q81/R81 -> 0.021818182
A82: =A81+1 -> 80 | B82: FE-275 | C82: 46120 | D82: Victor Hugo | E82: 1-182 | F82: 7350 | G82: =F82*16% -> 1176 | H82: =F82+G82 -> 8526 | I82: P | J82: 46127 | L82: Lavado CN | M82: RAMA | O82: =P82/F82 -> 0.14285714 | P82: 1050 | Q82: 1050 | R82: 8400 | S82: =Q82/R82 -> 0.125
A83: =A82+1 -> 81 | B83: FE-276 | C83: 46120 | D83: Victor Hugo | E83: 1-184 | F83: 3675 | G83: =F83*16% -> 588 | H83: =F83+G83 -> 4263 | I83: P | J83: 46127 | L83: Lavado CN | M83: RAMA | O83: =P83/F83 -> 0.14285714 | P83: 525 | Q83: 525 | R83: 4200 | S83: =Q83/R83 -> 0.125
A84: =A83+1 -> 82 | B84: FE-277 | C84: 46125 | D84: Express | E84: N/A | F84: 3225 | G84: =F84*16% -> 516 | H84: =F84+G84 -> 3741 | I84: p | K84: N/A | L84: Otro | M84: Otro | O84: =P84/F84 -> 1 | P84: 3225 | Q84: 0 | R84: 0 | S84: 0
A85: =A84+1 -> 83 | B85: FE-278 | C85: 46126 | D85: Victor Hugo | E85: 1-185 | F85: 525 | G85: =F85*16% -> 84 | H85: =F85+G85 -> 609 | I85: P | J85: 46142 | L85: Lavado CN | M85: RAMA | O85: =P85/F85 -> 0 | S85: =Q85/R85 -> #DIV/0!
A86: =A85+1 -> 84 | B86: FE-279 | C86: 46126 | D86: Victor Hugo | E86: 1-187 | F86: 600 | G86: =F86*16% -> 96 | H86: =F86+G86 -> 696 | I86: P | J86: 46142 | L86: Lavado CN | M86: Jenny | O86: =P86/F86 -> 0 | P86: 0 | Q86: 0 | R86: 600 | S86: =Q86/R86 -> 0
A87: =A86+1 -> 85 | B87: FE-280 | C87: 46126 | D87: Victor Hugo | E87: 1-190 | F87: 1475 | G87: =F87*16% -> 236 | H87: =F87+G87 -> 1711 | I87: P | J87: 46142 | L87: Lavado CN | M87: RAMA | O87: =P87/F87 -> 0.28813559 | P87: 425 | Q87: 425 | R87: 1900 | S87: =Q87/R87 -> 0.22368421
A88: =A87+1 -> 86 | B88: FE-281 | C88: 46126 | D88: Victor Hugo | E88: 1-192 | F88: 9830 | G88: =F88*16% -> 1572.8 | H88: =F88+G88 -> 11402.8 | I88: P | J88: 46142 | L88: Flete | M88: Jenny | O88: =P88/F88 -> 0.27772126 | P88: 2730 | Q88: 1170 | R88: 11000 | S88: =Q88/R88 -> 0.10636364
A89: =A88+1 -> 87 | B89: FE-282 | C89: 46129 | D89: Victor Hugo | E89: 1-194 | F89: 5200 | G89: =F89*16% -> 832 | H89: =F89+G89 -> 6032 | I89: P | J89: 46142 | L89: LOCAL CN | M89: Jenny | O89: =P89/F89 -> 0.13461538 | P89: 700 | Q89: 300 | R89: 5500 | S89: =Q89/R89 -> 0.054545455
A90: =A89+1 -> 88 | B90: FE-283 | C90: 46129 | D90: Victor Hugo | E90: 1-197 | F90: 18080 | G90: =F90*16% -> 2892.8 | H90: =F90+G90 -> 20972.8 | I90: P | J90: 46142 | L90: LOCAL CN | M90: Jenny | O90: =P90/F90 -> 0.33517699 | P90: 6060 | Q90: 1520 | R90: 19600 | S90: =Q90/R90 -> 0.07755102
A91: =A90+1 -> 89 | B91: FE-284 | C91: 46129 | D91: Victor Hugo | E91: 1-198 | F91: 44800 | G91: =F91*16% -> 7168 | H91: =F91+G91 -> 51968 | I91: P | J91: 46142 | L91: Flete | M91: RAMA | O91: =P91/F91 -> 0.10714286 | P91: 4800 | Q91: 1200 | R91: 46000 | S91: =Q91/R91 -> 0.026086957
A92: =A91+1 -> 90 | B92: FE-285 | C92: 46129 | D92: Cancelado | E92: 1-201 | F92: 0 | G92: =F92*16% -> 0 | H92: =F92+G92 -> 0 | I92: X | J92: 46142 | L92: Flete | M92: RAMA | O92: 0 | P92: 0 | Q92: 0 | R92: 0 | S92: 0
A93: =A92+1 -> 91 | B93: FE-286 | C93: 46130 | D93: Victor Hugo | E93: 1-201 | F93: 71400 | G93: =F93*16% -> 11424 | H93: =F93+G93 -> 82824 | I93: P | J93: 46142 | L93: Flete | M93: RAMA | O93: =P93/F93 -> 0.089635854 | P93: 6400 | Q93: 1600 | R93: 72000 | S93: =Q93/R93 -> 0.022222222
A94: =A93+1 -> 92 | B94: FE-287 | C94: 46132 | D94: Victor Hugo | E94: 1-203 | F94: 2100 | G94: =F94*16% -> 336 | H94: =F94+G94 -> 2436 | I94: P | J94: 46157 | L94: Lavado CN | M94: RAMA | O94: =P94/F94 -> 0.14285714 | P94: 300 | Q94: 300 | R94: 2400 | S94: =Q94/R94 -> 0.125
A95: =A94+1 -> 93 | B95: FE-288 | C95: 46132 | D95: Victor Hugo | E95: 1-204 | F95: 950 | G95: =F95*16% -> 152 | H95: =F95+G95 -> 1102 | I95: P | J95: 46157 | L95: Lavado CN | M95: RAMA | O95: =P95/F95 -> 0.36842105 | P95: 350 | Q95: 350 | R95: 1300 | S95: =Q95/R95 -> 0.26923077
A96: =A95+1 -> 94 | B96: FE-289 | C96: 46140 | D96: RAMA | E96: N/A | F96: 3000 | G96: =F96*16% -> 480 | H96: =F96+G96 -> 3480 | I96: P | J96: 46142 | L96: Coordinacion | M96: N/A | O96: =P96/F96 -> 1 | P96: 3000 | Q96: 0 | R96: 0 | S96: =Q96/R96 -> #DIV/0!
A97: =A96+1 -> 95 | B97: FE-290 | C97: 46140 | D97: Victor Hugo | E97: 1-208 | F97: 38800 | G97: =F97*16% -> 6208 | H97: =F97+G97 -> 45008 | I97: P | J97: 46157 | L97: Coordinacion | M97: N/A | O97: =P97/F97 -> 0.12371134 | P97: 4800 | Q97: 1200 | R97: 40000 | S97: =Q97/R97 -> 0.03
A98: =A97+1 -> 96 | B98: FE-291 | C98: 46140 | D98: Express | E98: N/A | F98: 500 | G98: =F98*16% -> 80 | H98: =F98+G98 -> 580 | I98: P | J98: 46157 | L98: Coordinacion | M98: N/A | O98: =P98/F98 -> 1 | P98: 500 | Q98: 0 | R98: 0 | S98: =Q98/R98 -> #DIV/0!
A99: =A98+1 -> 97 | B99: FE-292 | C99: 46146 | D99: Victor Hugo | E99: 1-211 | F99: 41750 | G99: =F99*16% -> 6680 | H99: =F99+G99 -> 48430 | I99: P | J99: 46157 | L99: Flete | M99: RAMA | O99: =P99/F99 -> 0.041916168 | P99: 1750 | Q99: 750 | R99: 42500 | S99: =Q99/R99 -> 0.017647059
A100: =A99+1 -> 98 | B100: FE-293 | C100: 46146 | D100: Victor Hugo | E100: 1-212 | F100: 65800 | G100: =F100*16% -> 10528 | H100: =F100+G100 -> 76328 | I100: P | J100: 46157 | L100: Flete | M100: RAMA | O100: =P100/F100 -> 0.018237082 | P100: 1200 | Q100: 4800 | R100: 67000 | S100: =Q100/R100 -> 0.071641791
...

Sheet Hoja1
C3: FECHA DE QUINCENA
